Workbook

Sheet Cover
B2: Project "X" Financial Model
B4: Model Overview (Обзор модели) | C4: Model Overview (Обзор модели) | D4: Model Overview (Обзор модели) | E4: Model Overview (Обзор модели) | F4: Model Overview (Обзор модели)
B5: Version | C5: GitHub Final — Fixed
B6: Purpose | C6: Financial model for Project X with a 36-month forecast, scenario selection, unit economics, P&L, cash flow, valuation and sensitivity analysis.
B7: Language | C7: English with Russian translations in brackets
B8: Scenario logic | C8: Change the selected scenario in Assumptions!C5. Model outputs update through formula-based scenario multipliers.
B9: Monetization | C9: Commission, Premium, Partnerships, Advertising, Promoted Listings, Paid Listings
B10: Prepared for | C10: GitHub portfolio / Junior Financial Analyst case
B11: Date | C11: 2026-05-30
B12: Note | C12: Synthetic assumptions for planning and portfolio purposes.
B15: Sheets (Листы) | C15: Sheets (Листы) | D15: Sheets (Листы) | E15: Sheets (Листы) | F15: Sheets (Листы)
B16: Assumptions | C16: Inputs and scenario selector
B17: Monthly Model | C17: 36-month operating model
B18: Annual Summary | C18: Annual output summary
B19: Unit Economics | C19: ARPU, CAC, LTV, LTV/CAC, Payback
B20: P&L | C20: Profit and loss
B21: Cash Flow | C21: Free cash flow and discounted cash flow
B22: Valuation | C22: NPV, IRR, revenue multiple valuation
B23: Sensitivity | C23: Revenue sensitivity table
B24: Dashboard | C24: Charts and KPI dashboard
B25: README Notes | C25: Notes for GitHub README

Sheet Assumptions
B2: Assumptions (Допущения)
B4: Scenario Control (Выбор сценария) | C4: Scenario Control (Выбор сценария) | D4: Scenario Control (Выбор сценария) | E4: Scenario Control (Выбор сценария) | F4: Scenario Control (Выбор сценария)
B5: Selected Scenario (Выбранный сценарий) | C5: Base | H5: Conservative
B6: Discount Rate (Ставка дисконтирования) | C6: 0.18 | H6: Base
B7: Initial Investment (Первоначальные инвестиции) | C7: 1000000 | H7: Optimistic
B8: Model Start (Начало модели) | C8: Jan-2026
B10: Core Business Inputs (Ключевые бизнес-допущения) | C10: Core Business Inputs (Ключевые бизнес-допущения) | D10: Core Business Inputs (Ключевые бизнес-допущения) | E10: Core Business Inputs (Ключевые бизнес-допущения) | F10: Core Business Inputs (Ключевые бизнес-допущения)
B11: Input (Допущение) | C11: Value (Значение) | D11: Unit (Ед.)
B12: Initial Active Users (Активные пользователи M1) | C12: 2500 | D12: users
B13: Monthly Growth (Месячный рост пользователей) | C13: 0.055 | D13: %
B14: Monthly Churn (Месячный отток) | C14: 0.035 | D14: %
B15: Conversion to Deal (Конверсия в сделку) | C15: 0.15 | D15: %
B16: Average Rent (Средняя аренда) | C16: 25000 | D16: ₽
B17: Average Commission (Средняя комиссия) | C17: 0.04 | D17: %
B18: Premium Price (Цена Premium) | C18: 399 | D18: ₽ / month
B19: Premium Conversion (Конверсия в Premium) | C19: 0.05 | D19: %
B20: Partnership Revenue / User (Партнёрки на пользователя) | C20: 14 | D20: ₽ / user / month
B21: Advertising Revenue / User (Реклама на пользователя) | C21: 6 | D21: ₽ / user / month
B22: Listings per User (Объявлений на пользователя) | C22: 0.4 | D22: listings
B23: Promoted Listing Price (Цена продвижения) | C23: 199 | D23: ₽
... B29: Average Customer Lifetime (Средний срок жизни клиента) | C29: 12 | D29: months
B31: Cost Inputs (Расходные допущения) | C31: Cost Inputs (Расходные допущения) | D31: Cost Inputs (Расходные допущения) | E31: Cost Inputs (Расходные допущения) | F31: Cost Inputs (Расходные допущения)
B32: Cost Item (Статья расхода) | C32: Value (Значение)
B33: Development / Month (Разработка / месяц) | C33: 120000
B34: Marketing / Month (Маркетинг / месяц) | C34: 120000
B35: Hosting / Month (Хостинг / месяц) | C35: 25000
B36: Legal & Admin / Month (Юр. и админ. / месяц) | C36: 20000
B37: Support / Month (Поддержка / месяц) | C37: 35000
B38: Other Expenses / Month (Прочие расходы / месяц) | C38: 25000
B39: Variable Cost per Deal (Переменные расходы на сделку) | C39: 150
B42: Scenario Multipliers (Мультипликаторы сценариев) | C42: Scenario Multipliers (Мультипликаторы сценариев) | D42: Scenario Multipliers (Мультипликаторы сценариев) | E42: Scenario Multipliers (Мультипликаторы сценариев) | F42: Scenario Multipliers (Мультипликаторы сценариев)
B43: Metric (Метрика) | C43: Conservative | D43: Base | E43: Optimistic
B44: User Growth Multiplier | C44: 0.7 | D44: 1 | E44: 1.35
B45: Conversion Multiplier | C45: 0.8 | D45: 1 | E45: 1.2
B46: Premium Conversion Multiplier | C46: 0.75 | D46: 1 | E46: 1.25
B47: CAC Multiplier | C47: 1.25 | D47: 1 | E47: 0.85
B48: Cost Multiplier | C48: 1.05 | D48: 1 | E48: 1.1

Sheet Monthly Model
B2: Monthly Model (Помесячная модель)
B4: 36-Month Operating Forecast (36-месячный операционный прогноз) | C4: 36-Month Operating Forecast (36-месячный операционный прогноз) | D4: 36-Month Operating Forecast (36-месячный операционный прогноз) | E4: 36-Month Operating Forecast (36-месячный операционный прогноз) | F4: 36-Month Operating Forecast (36-месячный операционный прогноз) | G4: 36-Month Operating Forecast (36-месячный операционный прогноз) | H4: 36-Month Operating Forecast (36-месячный операционный прогноз) | I4: 36-Month Operating Forecast (36-месячный операционный прогноз) | J4: 36-Month Operating Forecast (36-месячный операционный прогноз) | K4: 36-Month Operating Forecast (36-месячный операционный прогноз) | L4: 36-Month Operating Forecast (36-месячный операционный прогноз) | M4: 36-Month Operating Forecast (36-месячный операционный прогноз) | N4: 36-Month Operating Forecast (36-месячный операционный прогноз) | O4: 36-Month Operating Forecast (36-месячный операционный прогноз) | P4: 36-Month Operating Forecast (36-месячный операционный прогноз) | Q4: 36-Month Operating Forecast (36-месячный операционный прогноз) | R4: 36-Month Operating Forecast (36-месячный операционный прогноз) | S4: 36-Month Operating Forecast (36-месячный операционный прогноз) | T4: 36-Month Operating Forecast (36-месячный операционный прогноз) | U4: 36-Month Operating Forecast (36-месячный операционный прогноз) | V4: 36-Month Operating Forecast (36-месячный операционный прогноз) | W4: 36-Month Operating Forecast (36-месячный операционный прогноз) | X4: 36-Month Operating Forecast (36-месячный операционный прогноз) | Y4: 36-Month Operating Forecast (36-месячный операционный прогноз) | Z4: 36-Month Operating Forecast (36-месячный операционный прогноз) | AA4: 36-Month Operating Forecast (36-месячный операционный прогноз) | AB4: 36-Month Operating Forecast (36-месячный операционный прогноз) | AC4: 36-Month Operating Forecast (36-месячный операционный прогноз) | AD4: 36-Month Operating Forecast (36-месячный операционный прогноз) | AE4: 36-Month Operating Forecast (36-месячный операционный прогноз) | AF4: 36-Month Operating Forecast (36-месячный операционный прогноз) | AG4: 36-Month Operating Forecast (36-месячный операционный прогноз) | AH4: 36-Month Operating Forecast (36-месячный операционный прогноз) | AI4: 36-Month Operating Forecast (36-месячный операционный прогноз) | AJ4: 36-Month Operating Forecast (36-месячный операционный прогноз) | AK4: 36-Month Operating Forecast (36-месячный операционный прогноз) | AL4: 36-Month Operating Forecast (36-месячный операционный прогноз) | AM4: 36-Month Operating Forecast (36-месячный операционный прогноз)
B5: Metric (Метрика) | C5: M1 | D5: M2 | E5: M3 | F5: M4 | G5: M5 | H5: M6 | I5: M7 | J5: M8 | K5: M9 | L5: M10 | M5: M11 | N5: M12 | O5: M13 | P5: M14 | Q5: M15 | R5: M16 | S5: M17 | T5: M18 | U5: M19 | V5: M20 | W5: M21 | X5: M22 | Y5: M23 | Z5: M24 | AA5: M25 | AB5: M26 | AC5: M27 | AD5: M28 | AE5: M29 | AF5: M30 | AG5: M31 | AH5: M32 | AI5: M33 | AJ5: M34 | AK5: M35 | AL5: M36
B6: Year (Год) | C6: 2026 | D6: 2026 | E6: 2026 | F6: 2026 | G6: 2026 | H6: 2026 | I6: 2026 | J6: 2026 | K6: 2026 | L6: 2026 | M6: 2026 | N6: 2026 | O6: 2027 | P6: 2027 | Q6: 2027 | R6: 2027 | S6: 2027 | T6: 2027 | U6: 2027 | V6: 2027 | W6: 2027 | X6: 2027 | Y6: 2027 | Z6: 2027 | AA6: 2028 | AB6: 2028 | AC6: 2028 | AD6: 2028 | AE6: 2028 | AF6: 2028 | AG6: 2028 | AH6: 2028 | AI6: 2028 | AJ6: 2028 | AK6: 2028 | AL6: 2028
B7: Active Users (Активные пользователи) | C7: =Assumptions!$C$12 -> 2500 | D7: =C7+D8-D9 -> 2550 | E7: =D7+E8-E9 -> 2601 | F7: =E7+F8-F9 -> 2653.02 | G7: =F7+G8-G9 -> 2706.0804 | H7: =G7+H8-H9 -> 2760.202 | I7: =H7+I8-I9 -> 2815.406 | J7: =I7+J8-J9 -> 2871.7142 | K7: =J7+K8-K9 -> 2929.1485 | ... AL7: =AK7+AL8-AL9 -> 4999.7239
B8: New Users (Новые пользователи) | C8: =Assumptions!$C$12 -> 2500 | D8: =C7*Assumptions!$C$13*INDEX(Assumptions!$C$44:$E$44,1,MATCH(Assumptions!$C$5,Assumptions!$C$43:$E$43,0)) -> 137.5 | E8: =D7*Assumptions!$C$13*INDEX(Assumptions!$C$44:$E$44,1,MATCH(Assumptions!$C$5,Assumptions!$C$43:$E$43,0)) -> 140.25 | F8: =E7*Assumptions!$C$13*INDEX(Assumptions!$C$44:$E$44,1,MATCH(Assumptions!$C$5,Assumptions!$C$43:$E$43,0)) -> 143.055 | G8: =F7*Assumptions!$C$13*INDEX(Assumptions!$C$44:$E$44,1,MATCH(Assumptions!$C$5,Assumptions!$C$43:$E$43,0)) -> 145.9161 | H8: =G7*Assumptions!$C$13*INDEX(Assumptions!$C$44:$E$44,1,MATCH(Assumptions!$C$5,Assumptions!$C$43:$E$43,0)) -> 148.83442 | I8: =H7*Assumptions!$C$13*INDEX(Assumptions!$C$44:$E$44,1,MATCH(Assumptions!$C$5,Assumptions!$C$43:$E$43,0)) -> 151.81111 | J8: =I7*Assumptions!$C$13*INDEX(Assumptions!$C$44:$E$44,1,MATCH(Assumptions!$C$5,Assumptions!$C$43:$E$43,0)) -> 154.84733 | K8: =J7*Assumptions!$C$13*INDEX(Assumptions!$C$44:$E$44,1,MATCH(Assumptions!$C$5,Assumptions!$C$43:$E$43,0)) -> 157.94428 | ... AL8: =AK7*Assumptions!$C$13*INDEX(Assumptions!$C$44:$E$44,1,MATCH(Assumptions!$C$5,Assumptions!$C$43:$E$43,0)) -> 269.59295
B9: Churned Users (Ушедшие пользователи) | C9: =0 -> 0 | D9: =C7*Assumptions!$C$14 -> 87.5 | E9: =D7*Assumptions!$C$14 -> 89.25 | F9: =E7*Assumptions!$C$14 -> 91.035 | G9: =F7*Assumptions!$C$14 -> 92.8557 | H9: =G7*Assumptions!$C$14 -> 94.712814 | I9: =H7*Assumptions!$C$14 -> 96.60707 | J9: =I7*Assumptions!$C$14 -> 98.539212 | K9: =J7*Assumptions!$C$14 -> 100.51 | ... AL9: =AK7*Assumptions!$C$14 -> 171.55915
B10: Successful Deals (Успешные сделки) | C10: =C7*Assumptions!$C$15*INDEX(Assumptions!$C$45:$E$45,1,MATCH(Assumptions!$C$5,Assumptions!$C$43:$E$43,0)) -> 375 | D10: =D7*Assumptions!$C$15*INDEX(Assumptions!$C$45:$E$45,1,MATCH(Assumptions!$C$5,Assumptions!$C$43:$E$43,0)) -> 382.5 | E10: =E7*Assumptions!$C$15*INDEX(Assumptions!$C$45:$E$45,1,MATCH(Assumptions!$C$5,Assumptions!$C$43:$E$43,0)) -> 390.15 | F10: =F7*Assumptions!$C$15*INDEX(Assumptions!$C$45:$E$45,1,MATCH(Assumptions!$C$5,Assumptions!$C$43:$E$43,0)) -> 397.953 | G10: =G7*Assumptions!$C$15*INDEX(Assumptions!$C$45:$E$45,1,MATCH(Assumptions!$C$5,Assumptions!$C$43:$E$43,0)) -> 405.91206 | H10: =H7*Assumptions!$C$15*INDEX(Assumptions!$C$45:$E$45,1,MATCH(Assumptions!$C$5,Assumptions!$C$43:$E$43,0)) -> 414.0303 | I10: =I7*Assumptions!$C$15*INDEX(Assumptions!$C$45:$E$45,1,MATCH(Assumptions!$C$5,Assumptions!$C$43:$E$43,0)) -> 422.31091 | J10: =J7*Assumptions!$C$15*INDEX(Assumptions!$C$45:$E$45,1,MATCH(Assumptions!$C$5,Assumptions!$C$43:$E$43,0)) -> 430.75713 | ... AL10: =AL7*Assumptions!$C$15*INDEX(Assumptions!$C$45:$E$45,1,MATCH(Assumptions!$C$5,Assumptions!$C$43:$E$43,0)) -> 749.95858
B11: Transaction Commission Revenue (Комиссионная выручка) | C11: =C10*Assumptions!$C$16*Assumptions!$C$17 -> 375000 | D11: =D10*Assumptions!$C$16*Assumptions!$C$17 -> 382500 | E11: =E10*Assumptions!$C$16*Assumptions!$C$17 -> 390150 | F11: =F10*Assumptions!$C$16*Assumptions!$C$17 -> 397953 | G11: =G10*Assumptions!$C$16*Assumptions!$C$17 -> 405912.06 | H11: =H10*Assumptions!$C$16*Assumptions!$C$17 -> 414030.3 | I11: =I10*Assumptions!$C$16*Assumptions!$C$17 -> 422310.91 | J11: =J10*Assumptions!$C$16*Assumptions!$C$17 -> 430757.13 | ... AL11: =AL10*Assumptions!$C$16*Assumptions!$C$17 -> 749958.58
B12: Premium Subscribers (Premium-подписчики) | C12: =C7*Assumptions!$C$19*INDEX(Assumptions!$C$46:$E$46,1,MATCH(Assumptions!$C$5,Assumptions!$C$43:$E$43,0)) -> 125 | D12: =D7*Assumptions!$C$19*INDEX(Assumptions!$C$46:$E$46,1,MATCH(Assumptions!$C$5,Assumptions!$C$43:$E$43,0)) -> 127.5 | E12: =E7*Assumptions!$C$19*INDEX(Assumptions!$C$46:$E$46,1,MATCH(Assumptions!$C$5,Assumptions!$C$43:$E$43,0)) -> 130.05 | F12: =F7*Assumptions!$C$19*INDEX(Assumptions!$C$46:$E$46,1,MATCH(Assumptions!$C$5,Assumptions!$C$43:$E$43,0)) -> 132.651 | G12: =G7*Assumptions!$C$19*INDEX(Assumptions!$C$46:$E$46,1,MATCH(Assumptions!$C$5,Assumptions!$C$43:$E$43,0)) -> 135.30402 | H12: =H7*Assumptions!$C$19*INDEX(Assumptions!$C$46:$E$46,1,MATCH(Assumptions!$C$5,Assumptions!$C$43:$E$43,0)) -> 138.0101 | I12: =I7*Assumptions!$C$19*INDEX(Assumptions!$C$46:$E$46,1,MATCH(Assumptions!$C$5,Assumptions!$C$43:$E$43,0)) -> 140.7703 | J12: =J7*Assumptions!$C$19*INDEX(Assumptions!$C$46:$E$46,1,MATCH(Assumptions!$C$5,Assumptions!$C$43:$E$43,0)) -> 143.58571 | ... AL12: =AL7*Assumptions!$C$19*INDEX(Assumptions!$C$46:$E$46,1,MATCH(Assumptions!$C$5,Assumptions!$C$43:$E$43,0)) -> 249.98619
B13: Premium Revenue (Выручка Premium) | C13: =C12*Assumptions!$C$18 -> 49875 | D13: =D12*Assumptions!$C$18 -> 50872.5 | E13: =E12*Assumptions!$C$18 -> 51889.95 | F13: =F12*Assumptions!$C$18 -> 52927.749 | G13: =G12*Assumptions!$C$18 -> 53986.304 | H13: =H12*Assumptions!$C$18 -> 55066.03 | I13: =I12*Assumptions!$C$18 -> 56167.351 | J13: =J12*Assumptions!$C$18 -> 57290.698 | ... AL13: =AL12*Assumptions!$C$18 -> 99744.491
B14: Partnership Revenue (Партнёрская выручка) | C14: =C7*Assumptions!$C$20 -> 35000 | D14: =D7*Assumptions!$C$20 -> 35700 | E14: =E7*Assumptions!$C$20 -> 36414 | F14: =F7*Assumptions!$C$20 -> 37142.28 | G14: =G7*Assumptions!$C$20 -> 37885.126 | H14: =H7*Assumptions!$C$20 -> 38642.828 | I14: =I7*Assumptions!$C$20 -> 39415.685 | J14: =J7*Assumptions!$C$20 -> 40203.998 | ... AL14: =AL7*Assumptions!$C$20 -> 69996.134
B15: Advertising Revenue (Рекламная выручка) | C15: =C7*Assumptions!$C$21 -> 15000 | D15: =D7*Assumptions!$C$21 -> 15300 | E15: =E7*Assumptions!$C$21 -> 15606 | F15: =F7*Assumptions!$C$21 -> 15918.12 | G15: =G7*Assumptions!$C$21 -> 16236.482 | H15: =H7*Assumptions!$C$21 -> 16561.212 | I15: =I7*Assumptions!$C$21 -> 16892.436 | J15: =J7*Assumptions!$C$21 -> 17230.285 | ... AL15: =AL7*Assumptions!$C$21 -> 29998.343
B16: Listings (Объявления) | C16: =C7*Assumptions!$C$22 -> 1000 | D16: =D7*Assumptions!$C$22 -> 1020 | E16: =E7*Assumptions!$C$22 -> 1040.4 | F16: =F7*Assumptions!$C$22 -> 1061.208 | G16: =G7*Assumptions!$C$22 -> 1082.4322 | H16: =H7*Assumptions!$C$22 -> 1104.0808 | I16: =I7*Assumptions!$C$22 -> 1126.1624 | J16: =J7*Assumptions!$C$22 -> 1148.6857 | ... AL16: =AL7*Assumptions!$C$22 -> 1999.8896
B17: Promoted Listings Revenue (Продвижение объявлений) | C17: =C16*Assumptions!$C$24*Assumptions!$C$23 -> 39800 | D17: =D16*Assumptions!$C$24*Assumptions!$C$23 -> 40596 | E17: =E16*Assumptions!$C$24*Assumptions!$C$23 -> 41407.92 | F17: =F16*Assumptions!$C$24*Assumptions!$C$23 -> 42236.078 | G17: =G16*Assumptions!$C$24*Assumptions!$C$23 -> 43080.8 | H17: =H16*Assumptions!$C$24*Assumptions!$C$23 -> 43942.416 | I17: =I16*Assumptions!$C$24*Assumptions!$C$23 -> 44821.264 | J17: =J16*Assumptions!$C$24*Assumptions!$C$23 -> 45717.69 | ... AL17: =AL16*Assumptions!$C$24*Assumptions!$C$23 -> 79595.604
B18: Paid Listings Revenue (Платные объявления) | C18: =IF(1>=Assumptions!$C$25,C16*Assumptions!$C$27*Assumptions!$C$26,0) -> 0 | D18: =IF(2>=Assumptions!$C$25,D16*Assumptions!$C$27*Assumptions!$C$26,0) -> 0 | E18: =IF(3>=Assumptions!$C$25,E16*Assumptions!$C$27*Assumptions!$C$26,0) -> 0 | F18: =IF(4>=Assumptions!$C$25,F16*Assumptions!$C$27*Assumptions!$C$26,0) -> 0 | G18: =IF(5>=Assumptions!$C$25,G16*Assumptions!$C$27*Assumptions!$C$26,0) -> 0 | H18: =IF(6>=Assumptions!$C$25,H16*Assumptions!$C$27*Assumptions!$C$26,0) -> 0 | I18: =IF(7>=Assumptions!$C$25,I16*Assumptions!$C$27*Assumptions!$C$26,0) -> 0 | J18: =IF(8>=Assumptions!$C$25,J16*Assumptions!$C$27*Assumptions!$C$26,0) -> 0 | K18: =IF(9>=Assumptions!$C$25,K16*Assumptions!$C$27*Assumptions!$C$26,0) -> 0 | L18: =IF(10>=Assumptions!$C$25,L16*Assumptions!$C$27*Assumptions!$C$26,0) -> 0 | M18: =IF(11>=Assumptions!$C$25,M16*Assumptions!$C$27*Assumptions!$C$26,0) -> 0 | N18: =IF(12>=Assumptions!$C$25,N16*Assumptions!$C$27*Assumptions!$C$26,0) -> 0 | O18: =IF(13>=Assumptions!$C$25,O16*Assumptions!$C$27*Assumptions!$C$26,0) -> 0 | P18: =IF(14>=Assumptions!$C$25,P16*Assumptions!$C$27*Assumptions!$C$26,0) -> 0 | Q18: =IF(15>=Assumptions!$C$25,Q16*Assumptions!$C$27*Assumptions!$C$26,0) -> 0 | R18: =IF(16>=Assumptions!$C$25,R16*Assumptions!$C$27*Assumptions!$C$26,0) -> 0 | S18: =IF(17>=Assumptions!$C$25,S16*Assumptions!$C$27*Assumptions!$C$26,0) -> 0 | T18: =IF(18>=Assumptions!$C$25,T16*Assumptions!$C$27*Assumptions!$C$26,0) -> 0 | U18: =IF(19>=Assumptions!$C$25,U16*Assumptions!$C$27*Assumptions!$C$26,0) -> 0 | V18: =IF(20>=Assumptions!$C$25,V16*Assumptions!$C$27*Assumptions!$C$26,0) -> 0 | W18: =IF(21>=Assumptions!$C$25,W16*Assumptions!$C$27*Assumptions!$C$26,0) -> 0 | X18: =IF(22>=Assumptions!$C$25,X16*Assumptions!$C$27*Assumptions!$C$26,0) -> 0 | Y18: =IF(23>=Assumptions!$C$25,Y16*Assumptions!$C$27*Assumptions!$C$26,0) -> 0 | Z18: =IF(24>=Assumptions!$C$25,Z16*Assumptions!$C$27*Assumptions!$C$26,0) -> 0 | AA18: =IF(25>=Assumptions!$C$25,AA16*Assumptions!$C$27*Assumptions!$C$26,0) -> 38473.819 | AB18: =IF(26>=Assumptions!$C$25,AB16*Assumptions!$C$27*Assumptions!$C$26,0) -> 39243.295 | AC18: =IF(27>=Assumptions!$C$25,AC16*Assumptions!$C$27*Assumptions!$C$26,0) -> 40028.161 | AD18: =IF(28>=Assumptions!$C$25,AD16*Assumptions!$C$27*Assumptions!$C$26,0) -> 40828.725 | AE18: =IF(29>=Assumptions!$C$25,AE16*Assumptions!$C$27*Assumptions!$C$26,0) -> 41645.299 | AF18: =IF(30>=Assumptions!$C$25,AF16*Assumptions!$C$27*Assumptions!$C$26,0) -> 42478.205 | AG18: =IF(31>=Assumptions!$C$25,AG16*Assumptions!$C$27*Assumptions!$C$26,0) -> 43327.769 | AH18: =IF(32>=Assumptions!$C$25,AH16*Assumptions!$C$27*Assumptions!$C$26,0) -> 44194.324 | AI18: =IF(33>=Assumptions!$C$25,AI16*Assumptions!$C$27*Assumptions!$C$26,0) -> 45078.211 | AJ18: =IF(34>=Assumptions!$C$25,AJ16*Assumptions!$C$27*Assumptions!$C$26,0) -> 45979.775 | AK18: =IF(35>=Assumptions!$C$25,AK16*Assumptions!$C$27*Assumptions!$C$26,0) -> 46899.371 | AL18: =IF(36>=Assumptions!$C$25,AL16*Assumptions!$C$27*Assumptions!$C$26,0) -> 47837.358
B19: Total Revenue (Итого выручка) | C19: =SUM(C11,C13:C15,C17:C18) -> 514675 | D19: =SUM(D11,D13:D15,D17:D18) -> 524968.5 | E19: =SUM(E11,E13:E15,E17:E18) -> 535467.87 | F19: =SUM(F11,F13:F15,F17:F18) -> 546177.23 | G19: =SUM(G11,G13:G15,G17:G18) -> 557100.77 | H19: =SUM(H11,H13:H15,H17:H18) -> 568242.79 | I19: =SUM(I11,I13:I15,I17:I18) -> 579607.64 | J19: =SUM(J11,J13:J15,J17:J18) -> 591199.8 | ... AL19: =SUM(AL11,AL13:AL15,AL17:AL18) -> 1077130.5
B20: Variable Costs (Переменные расходы) | C20: =C10*Assumptions!$C$39 -> 56250 | D20: =D10*Assumptions!$C$39 -> 57375 | E20: =E10*Assumptions!$C$39 -> 58522.5 | F20: =F10*Assumptions!$C$39 -> 59692.95 | G20: =G10*Assumptions!$C$39 -> 60886.809 | H20: =H10*Assumptions!$C$39 -> 62104.545 | I20: =I10*Assumptions!$C$39 -> 63346.636 | J20: =J10*Assumptions!$C$39 -> 64613.569 | ... AL20: =AL10*Assumptions!$C$39 -> 112493.79
B21: Gross Profit (Валовая прибыль) | C21: =C19-C20 -> 458425 | D21: =D19-D20 -> 467593.5 | E21: =E19-E20 -> 476945.37 | F21: =F19-F20 -> 486484.28 | G21: =G19-G20 -> 496213.96 | H21: =H19-H20 -> 506138.24 | I21: =I19-I20 -> 516261.01 | J21: =J19-J20 -> 526586.23 | ... AL21: =AL19-AL20 -> 964636.73
B22: Fixed Operating Costs (Постоянные операционные расходы) | C22: =SUM(Assumptions!$C$33:'Assumptions'!$C$38)*INDEX(Assumptions!$C$48:$E$48,1,MATCH(Assumptions!$C$5,Assumptions!$C$43:$E$43,0)) -> 345000 | D22: =SUM(Assumptions!$C$33:'Assumptions'!$C$38)*INDEX(Assumptions!$C$48:$E$48,1,MATCH(Assumptions!$C$5,Assumptions!$C$43:$E$43,0)) -> 345000 | E22: =SUM(Assumptions!$C$33:'Assumptions'!$C$38)*INDEX(Assumptions!$C$48:$E$48,1,MATCH(Assumptions!$C$5,Assumptions!$C$43:$E$43,0)) -> 345000 | F22: =SUM(Assumptions!$C$33:'Assumptions'!$C$38)*INDEX(Assumptions!$C$48:$E$48,1,MATCH(Assumptions!$C$5,Assumptions!$C$43:$E$43,0)) -> 345000 | G22: =SUM(Assumptions!$C$33:'Assumptions'!$C$38)*INDEX(Assumptions!$C$48:$E$48,1,MATCH(Assumptions!$C$5,Assumptions!$C$43:$E$43,0)) -> 345000 | H22: =SUM(Assumptions!$C$33:'Assumptions'!$C$38)*INDEX(Assumptions!$C$48:$E$48,1,MATCH(Assumptions!$C$5,Assumptions!$C$43:$E$43,0)) -> 345000 | I22: =SUM(Assumptions!$C$33:'Assumptions'!$C$38)*INDEX(Assumptions!$C$48:$E$48,1,MATCH(Assumptions!$C$5,Assumptions!$C$43:$E$43,0)) -> 345000 | J22: =SUM(Assumptions!$C$33:'Assumptions'!$C$38)*INDEX(Assumptions!$C$48:$E$48,1,MATCH(Assumptions!$C$5,Assumptions!$C$43:$E$43,0)) -> 345000 | ... AL22: =SUM(Assumptions!$C$33:'Assumptions'!$C$38)*INDEX(Assumptions!$C$48:$E$48,1,MATCH(Assumptions!$C$5,Assumptions!$C$43:$E$43,0)) -> 345000
B23: EBITDA | C23: =C21-C22 -> 113425 | D23: =D21-D22 -> 122593.5 | E23: =E21-E22 -> 131945.37 | F23: =F21-F22 -> 141484.28 | G23: =G21-G22 -> 151213.96 | H23: =H21-H22 -> 161138.24 | I23: =I21-I22 -> 171261.01 | J23: =J21-J22 -> 181586.23 | ... AL23: =AL21-AL22 -> 619636.73
B24: EBITDA Margin (Маржа EBITDA) | C24: =IFERROR(C23/C19,0) -> 0.22038179 | D24: =IFERROR(D23/D19,0) -> 0.23352544 | E24: =IFERROR(E23/E19,0) -> 0.24641137 | F24: =IFERROR(F23/F19,0) -> 0.25904463 | G24: =IFERROR(G23/G19,0) -> 0.27143018 | H24: =IFERROR(H23/H19,0) -> 0.28357288 | I24: =IFERROR(I23/I19,0) -> 0.29547748 | J24: =IFERROR(J23/J19,0) -> 0.30714866 | ... AL24: =IFERROR(AL23/AL19,0) -> 0.57526615
B25: Free Cash Flow (Свободный денежный поток) | C25: =C23 -> 113425 | D25: =D23 -> 122593.5 | E25: =E23 -> 131945.37 | F25: =F23 -> 141484.28 | G25: =G23 -> 151213.96 | H25: =H23 -> 161138.24 | I25: =I23 -> 171261.01 | J25: =J23 -> 181586.23 | ... AL25: =AL23 -> 619636.73
B26: Closing Cash (Деньги на конец периода) | C26: =Assumptions!$C$7+C25 -> 1113425 | D26: =C26+D25 -> 1236018.5 | E26: =D26+E25 -> 1367963.9 | F26: =E26+F25 -> 1509448.1 | G26: =F26+G25 -> 1660662.1 | H26: =G26+H25 -> 1821800.4 | I26: =H26+I25 -> 1993061.4 | J26: =I26+J25 -> 2174647.6 | K26: =J26+K25 -> 2366765.5 | ... AL26: =AK26+AL25 -> 12931532

Sheet Annual Summary
B2: Annual Summary (Годовой итог)
B4: Annual Summary (Годовая сводка) | C4: Annual Summary (Годовая сводка) | D4: Annual Summary (Годовая сводка) | E4: Annual Summary (Годовая сводка)
B5: Metric (Метрика) | C5: 2026 | D5: 2027 | E5: 2028
B6: Active Users EOY (Активные пользователи на конец года) | C6: ='Monthly Model'!N7 -> 3108.4358 | D6: ='Monthly Model'!Z7 -> 3942.2482 | E6: ='Monthly Model'!AM7 -> 0
B7: Revenue (Выручка) | C7: =SUM('Monthly Model'!C19:N19) -> 6902867.3 | D7: =SUM('Monthly Model'!O19:Z19) -> 8754504.8 | E7: =SUM('Monthly Model'!AA19:AM19) -> 11618843
B8: EBITDA | C8: =SUM('Monthly Model'!C23:N23) -> 2008437.2 | D8: =SUM('Monthly Model'!O23:Z23) -> 3657705.1 | E8: =SUM('Monthly Model'!AA23:AM23) -> 6265389.8
B9: EBITDA Margin (Маржа EBITDA) | C9: =IFERROR(C8/C7,0) -> 0.29095695 | D9: =IFERROR(D8/D7,0) -> 0.41780834 | E9: =IFERROR(E8/E7,0) -> 0.53924386
B10: Free Cash Flow (Свободный денежный поток) | C10: =SUM('Monthly Model'!C25:N25) -> 2008437.2 | D10: =SUM('Monthly Model'!O25:Z25) -> 3657705.1 | E10: =SUM('Monthly Model'!AA25:AM25) -> 6265389.8
B11: Closing Cash (Деньги на конец года) | C11: ='Monthly Model'!N26 -> 3008437.2 | D11: ='Monthly Model'!Z26 -> 6666142.3 | E11: ='Monthly Model'!AM26 -> 0

Sheet Unit Economics
B2: Unit Economics (Юнит-экономика)
B4: Unit Economics (Юнит-экономика) | C4: Unit Economics (Юнит-экономика) | D4: Unit Economics (Юнит-экономика) | E4: Unit Economics (Юнит-экономика)
B5: Metric (Метрика) | C5: 2026 | D5: 2027 | E5: 2028
B6: Average Active Users (Средние активные пользователи) | C6: =AVERAGE('Monthly Model'!C7:N7) -> 2794.1854 | D6: =AVERAGE('Monthly Model'!O7:Z7) -> 3543.7027 | E6: =AVERAGE('Monthly Model'!AA7:AM7) -> 4494.2718
B7: Revenue (Выручка) | C7: ='Annual Summary'!C7 -> 6902867.3 | D7: ='Annual Summary'!D7 -> 8754504.8 | E7: ='Annual Summary'!E7 -> 11618843
B8: ARPU (Выручка на пользователя) | C8: =C7/C6 -> 2470.44 | D8: =D7/D6 -> 2470.44 | E8: =E7/E6 -> 2585.256
B9: CAC (Стоимость привлечения) | C9: =Assumptions!$C$28*INDEX(Assumptions!$C$47:$E$47,1,MATCH(Assumptions!$C$5,Assumptions!$C$43:$E$43,0)) -> 300 | D9: =Assumptions!$C$28*INDEX(Assumptions!$C$47:$E$47,1,MATCH(Assumptions!$C$5,Assumptions!$C$43:$E$43,0)) -> 300 | E9: =Assumptions!$C$28*INDEX(Assumptions!$C$47:$E$47,1,MATCH(Assumptions!$C$5,Assumptions!$C$43:$E$43,0)) -> 300
B10: LTV (Ценность клиента) | C10: =C8*Assumptions!$C$29 -> 29645.28 | D10: =D8*Assumptions!$C$29 -> 29645.28 | E10: =E8*Assumptions!$C$29 -> 31023.072
B11: LTV/CAC | C11: =IFERROR(C10/C9,0) -> 98.8176 | D11: =IFERROR(D10/D9,0) -> 98.8176 | E11: =IFERROR(E10/E9,0) -> 103.41024
B12: Payback Period, months (Срок окупаемости, мес.) | C12: =IFERROR(C9/(C8/12),0) -> 1.4572303 | D12: =IFERROR(D9/(D8/12),0) -> 1.4572303 | E12: =IFERROR(E9/(E8/12),0) -> 1.392512

Sheet P&L
B2: P&L (Отчет о прибылях и убытках)
B4: P&L Statement (Отчет о прибылях и убытках) | C4: P&L Statement (Отчет о прибылях и убытках) | D4: P&L Statement (Отчет о прибылях и убытках) | E4: P&L Statement (Отчет о прибылях и убытках)
B5: Metric (Метрика) | C5: 2026 | D5: 2027 | E5: 2028
B6: Revenue (Выручка) | C6: ='Annual Summary'!C7 -> 6902867.3 | D6: ='Annual Summary'!D7 -> 8754504.8 | E6: ='Annual Summary'!E7 -> 11618843
B7: Variable Costs (Переменные расходы) | C7: =SUM('Monthly Model'!C20:N20) -> 754430.05 | D7: =SUM('Monthly Model'!O20:Z20) -> 956799.72 | E7: =SUM('Monthly Model'!AA20:AM20) -> 1213453.4
B8: Gross Profit (Валовая прибыль) | C8: =C6-C7 -> 6148437.2 | D8: =D6-D7 -> 7797705.1 | E8: =E6-E7 -> 10405390
B9: Fixed Operating Costs (Постоянные операционные расходы) | C9: =SUM('Monthly Model'!C22:N22) -> 4140000 | D9: =SUM('Monthly Model'!O22:Z22) -> 4140000 | E9: =SUM('Monthly Model'!AA22:AM22) -> 4140000
B10: EBITDA | C10: =C8-C9 -> 2008437.2 | D10: =D8-D9 -> 3657705.1 | E10: =E8-E9 -> 6265389.8
B11: EBITDA Margin (Маржа EBITDA) | C11: =IFERROR(C10/C6,0) -> 0.29095695 | D11: =IFERROR(D10/D6,0) -> 0.41780834 | E11: =IFERROR(E10/E6,0) -> 0.53924386

Sheet Cash Flow
B2: Cash Flow (Денежный поток)
B4: Cash Flow Statement (Отчет о движении денежных средств) | D4: Cash Flow Statement (Отчет о движении денежных средств) | E4: Cash Flow Statement (Отчет о движении денежных средств) | F4: Cash Flow Statement (Отчет о движении денежных средств)
B5: Metric (Метрика) | C5: Year 0 | D5: 2026 | E5: 2027 | F5: 2028
B6: Initial Investment (Инвестиции) | C6: -1000000 | E6: =0 -> 0 | F6: =0 -> 0
B7: Free Cash Flow (Свободный денежный поток) | D7: ='Annual Summary'!C10 -> 2008437.2 | E7: ='Annual Summary'!D10 -> 3657705.1 | F7: ='Annual Summary'!E10 -> 6265389.8
B8: Net Cash Flow (Чистый денежный поток) | C8: -1000000 | D8: =D6+D7 -> 2008437.2 | E8: =E6+E7 -> 3657705.1 | F8: =F6+F7 -> 6265389.8
B9: Closing Cash (Деньги на конец года) | C9: -1000000 | D9: =D8 -> 2008437.2 | E9: =D9+E8 -> 5666142.3 | F9: =E9+F8 -> 11931532
B10: Discounted FCF (Дисконтированный FCF) | C10: -1000000 | D10: =D7/(1+Assumptions!$C$6)^1 -> 1702065.5 | E10: =E7/(1+Assumptions!$C$6)^2 -> 2626906.8 | F10: =F7/(1+Assumptions!$C$6)^3 -> 3813309.7

Sheet Valuation
B2: Valuation (Оценка стоимости)
B4: Valuation (Оценка стоимости) | C4: Valuation (Оценка стоимости)
B5: Metric (Метрика) | C5: Value (Значение)
B6: NPV (Чистая приведенная стоимость) | C6: =SUM('Cash Flow'!D10:F10)-Assumptions!$C$7 -> 7142281.9
B7: IRR (IRR) | C7: =IRR('Cash Flow'!C8:F8) -> 2.5410511
B8: Revenue Multiple (Мультипликатор выручки) | C8: 3
B9: Implied Valuation (Оценка по выручке) | C9: ='Annual Summary'!E7*C8 -> 34856530
B10: Total 3Y EBITDA (EBITDA за 3 года) | C10: =SUM('Annual Summary'!C8:E8) -> 11931532

Sheet Sensitivity
B2: Sensitivity (Чувствительность)
B4: Year 1 Revenue Sensitivity (Чувствительность выручки Year 1) | C4: Year 1 Revenue Sensitivity (Чувствительность выручки Year 1) | D4: Year 1 Revenue Sensitivity (Чувствительность выручки Year 1) | E4: Year 1 Revenue Sensitivity (Чувствительность выручки Year 1) | F4: Year 1 Revenue Sensitivity (Чувствительность выручки Year 1)
B5: Deal Conversion / Commission | C5: 0.03 | D5: 0.04 | E5: 0.05 | F5: Comment
B6: 0.1 | C6: =Assumptions!$C$12*$B6*Assumptions!$C$16*VALUE(SUBSTITUTE(C$5,"%",""))/100+Assumptions!$C$12*Assumptions!$C$19*Assumptions!$C$18*12+Assumptions!$C$12*Assumptions!$C$20*12+Assumptions!$C$12*Assumptions!$C$21*12+Assumptions!$C$12*Assumptions!$C$22*Assumptions!$C$24*Assumptions!$C$23*12 -> 1677975 | D6: =Assumptions!$C$12*$B6*Assumptions!$C$16*VALUE(SUBSTITUTE(D$5,"%",""))/100+Assumptions!$C$12*Assumptions!$C$19*Assumptions!$C$18*12+Assumptions!$C$12*Assumptions!$C$20*12+Assumptions!$C$12*Assumptions!$C$21*12+Assumptions!$C$12*Assumptions!$C$22*Assumptions!$C$24*Assumptions!$C$23*12 -> 1678600 | E6: =Assumptions!$C$12*$B6*Assumptions!$C$16*VALUE(SUBSTITUTE(E$5,"%",""))/100+Assumptions!$C$12*Assumptions!$C$19*Assumptions!$C$18*12+Assumptions!$C$12*Assumptions!$C$20*12+Assumptions!$C$12*Assumptions!$C$21*12+Assumptions!$C$12*Assumptions!$C$22*Assumptions!$C$24*Assumptions!$C$23*12 -> 1679225 | F6: Low conversion
B7: 0.15 | C7: =Assumptions!$C$12*$B7*Assumptions!$C$16*VALUE(SUBSTITUTE(C$5,"%",""))/100+Assumptions!$C$12*Assumptions!$C$19*Assumptions!$C$18*12+Assumptions!$C$12*Assumptions!$C$20*12+Assumptions!$C$12*Assumptions!$C$21*12+Assumptions!$C$12*Assumptions!$C$22*Assumptions!$C$24*Assumptions!$C$23*12 -> 1678912.5 | D7: =Assumptions!$C$12*$B7*Assumptions!$C$16*VALUE(SUBSTITUTE(D$5,"%",""))/100+Assumptions!$C$12*Assumptions!$C$19*Assumptions!$C$18*12+Assumptions!$C$12*Assumptions!$C$20*12+Assumptions!$C$12*Assumptions!$C$21*12+Assumptions!$C$12*Assumptions!$C$22*Assumptions!$C$24*Assumptions!$C$23*12 -> 1679850 | E7: =Assumptions!$C$12*$B7*Assumptions!$C$16*VALUE(SUBSTITUTE(E$5,"%",""))/100+Assumptions!$C$12*Assumptions!$C$19*Assumptions!$C$18*12+Assumptions!$C$12*Assumptions!$C$20*12+Assumptions!$C$12*Assumptions!$C$21*12+Assumptions!$C$12*Assumptions!$C$22*Assumptions!$C$24*Assumptions!$C$23*12 -> 1680787.5 | F7: Base case
B8: 0.2 | C8: =Assumptions!$C$12*$B8*Assumptions!$C$16*VALUE(SUBSTITUTE(C$5,"%",""))/100+Assumptions!$C$12*Assumptions!$C$19*Assumptions!$C$18*12+Assumptions!$C$12*Assumptions!$C$20*12+Assumptions!$C$12*Assumptions!$C$21*12+Assumptions!$C$12*Assumptions!$C$22*Assumptions!$C$24*Assumptions!$C$23*12 -> 1679850 | D8: =Assumptions!$C$12*$B8*Assumptions!$C$16*VALUE(SUBSTITUTE(D$5,"%",""))/100+Assumptions!$C$12*Assumptions!$C$19*Assumptions!$C$18*12+Assumptions!$C$12*Assumptions!$C$20*12+Assumptions!$C$12*Assumptions!$C$21*12+Assumptions!$C$12*Assumptions!$C$22*Assumptions!$C$24*Assumptions!$C$23*12 -> 1681100 | E8: =Assumptions!$C$12*$B8*Assumptions!$C$16*VALUE(SUBSTITUTE(E$5,"%",""))/100+Assumptions!$C$12*Assumptions!$C$19*Assumptions!$C$18*12+Assumptions!$C$12*Assumptions!$C$20*12+Assumptions!$C$12*Assumptions!$C$21*12+Assumptions!$C$12*Assumptions!$C$22*Assumptions!$C$24*Assumptions!$C$23*12 -> 1682350 | F8: High conversion
B10: Note: the table estimates Year 1 revenue under different conversion and commission assumptions. It is separated from the scenario selector.

Sheet Dashboard
B2: Dashboard (Дашборд)
B4: Project "X" Financial Model Dashboard (Дашборд финансовой модели) | C4: Project "X" Financial Model Dashboard (Дашборд финансовой модели) | D4: Project "X" Financial Model Dashboard (Дашборд финансовой модели) | E4: Project "X" Financial Model Dashboard (Дашборд финансовой модели) | F4: Project "X" Financial Model Dashboard (Дашборд финансовой модели) | G4: Project "X" Financial Model Dashboard (Дашборд финансовой модели) | H4: Project "X" Financial Model Dashboard (Дашборд финансовой модели) | I4: Project "X" Financial Model Dashboard (Дашборд финансовой модели) | J4: Project "X" Financial Model Dashboard (Дашборд финансовой модели)
B6: Metric | C6: 2026 | D6: 2027 | E6: 2028 | G6: Metric | H6: Value | J6: Metric | K6: Value
B7: Revenue | C7: ='Annual Summary'!C7 -> 6902867.3 | D7: ='Annual Summary'!D7 -> 8754504.8 | E7: ='Annual Summary'!E7 -> 11618843 | G7: NPV | H7: =Valuation!C6 -> 7142281.9 | J7: Scenario | K7: =Assumptions!C5 -> Base
B8: EBITDA | C8: ='Annual Summary'!C8 -> 2008437.2 | D8: ='Annual Summary'!D8 -> 3657705.1 | E8: ='Annual Summary'!E8 -> 6265389.8 | G8: Implied Valuation | H8: =Valuation!C9 -> 34856530 | J8: LTV/CAC 2028 | K8: ='Unit Economics'!E11 -> 103.41024
B12: Metric | C12: 2026 | D12: 2027 | E12: 2028 | L12: Metric | M12: 2026 | N12: 2027 | O12: 2028
B13: Revenue | C13: ='Annual Summary'!C7 -> 6902867.3 | D13: ='Annual Summary'!D7 -> 8754504.8 | E13: ='Annual Summary'!E7 -> 11618843 | L13: Active Users | M13: ='Annual Summary'!C6 -> 3108.4358 | N13: ='Annual Summary'!D6 -> 3942.2482 | O13: ='Annual Summary'!E6 -> 0
B14: EBITDA | C14: ='Annual Summary'!C8 -> 2008437.2 | D14: ='Annual Summary'!D8 -> 3657705.1 | E14: ='Annual Summary'!E8 -> 6265389.8

Sheet README Notes
B2: README Notes (Заметки для README)
B4: Repository name | C4: Project-X-Financial-Model
B5: Description | C5: Financial model for Project X with 36-month forecast, scenarios, unit economics, P&L, cash flow, valuation and sensitivity analysis.
B6: Files | C6: Excel financial model, dashboard screenshot, README.md, docs/model_overview.md
B7: Main skills | C7: Financial modeling, unit economics, P&L, cash flow, valuation, scenario analysis
B8: Revenue streams | C8: Commission, Premium, Partnerships, Advertising, Promoted Listings, Paid Listings
B9: Model status | C9: GitHub-ready
B10: Important note | C10: Synthetic data and assumptions for educational and portfolio purposes.
B11: Suggested resume bullet | C11: Built a financial model for Project X including 36-month forecast, unit economics, P&L, cash flow, scenario analysis, valuation and sensitivity table.
B12: Next improvement | C12: Add real MVP user acquisition metrics when available.
